pcake/pcake.py
pcake-0.0.3.dist-info/LICENSE
pcake-0.0.3.dist-info/METADATA
pcake-0.0.3.dist-info/WHEEL
pcake-0.0.3.dist-info/top_level.txt
pcake-0.0.3.dist-info/RECORD
