Metadata-Version: 2.1
Name: pcake
Version: 0.0.3
Summary: Compare numeric properties from SPARQL endpoints
Home-page: https://github.com/oeg-upm/pcake
Author: Ahmad Alobaid
Author-email: aalobaid@fi.upm.es
License: Apache2
Platform: UNKNOWN
Classifier: Programming Language :: Python :: 3
Classifier: Programming Language :: Python :: 3.9
License-File: LICENSE
Requires-Dist: numpy
Requires-Dist: pandas
Requires-Dist: six
Requires-Dist: seaborn
